<?xml version="1.0" encoding="UTF-8"?>

<root>
  <data name="最近24小時船舶實際進港時間" note="中文船名後有★★為出發港或前ㄧ港為日本港口之船舶;中文船名後有★★★為出發港或前ㄧ港為仙台港、鹿島港、東京港、橫濱港、川崎港之船舶">
    <ship>
      <船舶種類>水泥船</船舶種類>
      <英文船名>TAHO OCEANIA</英文船名>
      <中文船名>達洋</中文船名>
      <實際進港時間>110/05/23 07:30</實際進港時間>
    </ship>
    <ship>
      <船舶種類>散裝船</船舶種類>
      <英文船名>TWINKLE SALUTE</英文船名>
      <中文船名>亮禮</中文船名>
      <實際進港時間>110/05/23 07:45</實際進港時間>
    </ship>
    <ship>
      <船舶種類>全貨櫃</船舶種類>
      <英文船名>SETSU MARU</英文船名>
      <中文船名>節丸★★</中文船名>
      <實際進港時間>110/05/23 07:45</實際進港時間>
    </ship>
    <ship>
      <船舶種類>油化船</船舶種類>
      <英文船名>SUN JUPITER</英文船名>
      <中文船名>木星</中文船名>
      <實際進港時間>110/05/23 07:55</實際進港時間>
    </ship>
    <ship>
      <船舶種類>雜貨船</船舶種類>
      <英文船名>ZAMBALES</英文船名>
      <中文船名>珍寶</中文船名>
      <實際進港時間>110/05/23 08:05</實際進港時間>
    </ship>
    <ship>
      <船舶種類>全貨櫃</船舶種類>
      <英文船名>YM INAUGURATION</英文船名>
      <中文船名>遠明</中文船名>
      <實際進港時間>110/05/23 08:10</實際進港時間>
    </ship>
    <ship>
      <船舶種類>雜貨船</船舶種類>
      <英文船名>NEW SAILING 1</英文船名>
      <中文船名>新航1</中文船名>
      <實際進港時間>110/05/23 08:45</實際進港時間>
    </ship>
    <ship>
      <船舶種類>全貨櫃</船舶種類>
      <英文船名>TENG YUN HE</英文船名>
      <中文船名>騰雲河</中文船名>
      <實際進港時間>110/05/23 09:25</實際進港時間>
    </ship>
    <ship>
      <船舶種類>油化船</船舶種類>
      <英文船名>VELEBIT</英文船名>
      <中文船名>韋萊比特</中文船名>
      <實際進港時間>110/05/23 09:40</實際進港時間>
    </ship>
    <ship>
      <船舶種類>雜貨船</船舶種類>
      <英文船名>YU TAI NO.1</英文船名>
      <中文船名>友泰1號</中文船名>
      <實際進港時間>110/05/23 09:50</實際進港時間>
    </ship>
    <ship>
      <船舶種類>散裝船</船舶種類>
      <英文船名>FPMC B 105</英文船名>
      <中文船名>台塑105</中文船名>
      <實際進港時間>110/05/23 10:00</實際進港時間>
    </ship>
    <ship>
      <船舶種類>全貨櫃</船舶種類>
      <英文船名>MAERSK DAVAO</英文船名>
      <中文船名>麥司克達沃</中文船名>
      <實際進港時間>110/05/23 10:15</實際進港時間>
    </ship>
    <ship>
      <船舶種類>全貨櫃</船舶種類>
      <英文船名>UNI-ACTIVE</英文船名>
      <中文船名>立沛</中文船名>
      <實際進港時間>110/05/23 10:45</實際進港時間>
    </ship>
    <ship>
      <船舶種類>雜貨船</船舶種類>
      <英文船名>XIN GUANG</英文船名>
      <中文船名>新光</中文船名>
      <實際進港時間>110/05/23 11:00</實際進港時間>
    </ship>
    <ship>
      <船舶種類>散裝船</船舶種類>
      <英文船名>CEMTEX SINCERITY</英文船名>
      <中文船名>裕誠</中文船名>
      <實際進港時間>110/05/23 11:20</實際進港時間>
    </ship>
    <ship>
      <船舶種類>水泥船</船舶種類>
      <英文船名>ASIA CEMENT NO.1</英文船名>
      <中文船名>亞泥1號</中文船名>
      <實際進港時間>110/05/23 11:30</實際進港時間>
    </ship>
    <ship>
      <船舶種類>漁船</船舶種類>
      <英文船名>DOLORES 872</英文船名>
      <中文船名>桃利絲872</中文船名>
      <實際進港時間>110/05/23 13:00</實際進港時間>
    </ship>
    <ship>
      <船舶種類>雜貨船</船舶種類>
      <英文船名>SOUTHERN ANGEL</英文船名>
      <中文船名>南方天使</中文船名>
      <實際進港時間>110/05/23 13:40</實際進港時間>
    </ship>
    <ship>
      <船舶種類>散裝船</船舶種類>
      <英文船名>OASIS ISLAND</英文船名>
      <中文船名>綠洲島</中文船名>
      <實際進港時間>110/05/23 14:20</實際進港時間>
    </ship>
    <ship>
      <船舶種類>油輪</船舶種類>
      <英文船名>TAIAN</英文船名>
      <中文船名>台安</中文船名>
      <實際進港時間>110/05/23 14:30</實際進港時間>
    </ship>
    <ship>
      <船舶種類>全貨櫃</船舶種類>
      <英文船名>WAN HAI 215</英文船名>
      <中文船名>兆春</中文船名>
      <實際進港時間>110/05/23 14:40</實際進港時間>
    </ship>
    <ship>
      <船舶種類>全貨櫃</船舶種類>
      <英文船名>UNI-PATRIOT</英文船名>
      <中文船名>立忠</中文船名>
      <實際進港時間>110/05/23 14:50</實際進港時間>
    </ship>
    <ship>
      <船舶種類>雜貨船</船舶種類>
      <英文船名>QUEEN YAN</英文船名>
      <中文船名>坤燕★★</中文船名>
      <實際進港時間>110/05/23 14:50</實際進港時間>
    </ship>
    <ship>
      <船舶種類>全貨櫃</船舶種類>
      <英文船名>FORMOSA CONTAINER NO.4</英文船名>
      <中文船名>台塑貨櫃4號</中文船名>
      <實際進港時間>110/05/23 15:05</實際進港時間>
    </ship>
    <ship>
      <船舶種類>散裝船</船舶種類>
      <英文船名>CEMTEX VENTURE</英文船名>
      <中文船名>裕勇輪</中文船名>
      <實際進港時間>110/05/23 16:10</實際進港時間>
    </ship>
    <ship>
      <船舶種類>油化船</船舶種類>
      <英文船名>DING HENG 5</英文船名>
      <中文船名>鼎衡5</中文船名>
      <實際進港時間>110/05/23 17:10</實際進港時間>
    </ship>
    <ship>
      <船舶種類>全貨櫃</船舶種類>
      <英文船名>WAN HAI 213</英文船名>
      <中文船名>恆春</中文船名>
      <實際進港時間>110/05/23 17:25</實際進港時間>
    </ship>
    <ship>
      <船舶種類>全貨櫃</船舶種類>
      <英文船名>EVER BRACE</英文船名>
      <中文船名>長固</中文船名>
      <實際進港時間>110/05/23 18:20</實際進港時間>
    </ship>
    <ship>
      <船舶種類>油化船</船舶種類>
      <英文船名>WOOLIM DRAGON 3</英文船名>
      <中文船名>又龍三號</中文船名>
      <實際進港時間>110/05/23 18:45</實際進港時間>
    </ship>
    <ship>
      <船舶種類>全貨櫃</船舶種類>
      <英文船名>WAN HAI 216</英文船名>
      <中文船名>耀春</中文船名>
      <實際進港時間>110/05/23 18:45</實際進港時間>
    </ship>
    <ship>
      <船舶種類>全貨櫃</船舶種類>
      <英文船名>CMA CGM MUSCA</英文船名>
      <中文船名>慕斯卡</中文船名>
      <實際進港時間>110/05/23 19:50</實際進港時間>
    </ship>
    <ship>
      <船舶種類>全貨櫃</船舶種類>
      <英文船名>HUA HANG 6</英文船名>
      <中文船名>華航6</中文船名>
      <實際進港時間>110/05/23 20:35</實際進港時間>
    </ship>
    <ship>
      <船舶種類>全貨櫃</船舶種類>
      <英文船名>THALASSA ELPIDA</英文船名>
      <中文船名>海望</中文船名>
      <實際進港時間>110/05/23 22:00</實際進港時間>
    </ship>
    <ship>
      <船舶種類>液化石油氣</船舶種類>
      <英文船名>ANTIKITHIRA</英文船名>
      <中文船名>安泰莉亞</中文船名>
      <實際進港時間>110/05/23 23:10</實際進港時間>
    </ship>
    <ship>
      <船舶種類>全貨櫃</船舶種類>
      <英文船名>HUA HANG 1</英文船名>
      <中文船名>華航1</中文船名>
      <實際進港時間>110/05/23 23:50</實際進港時間>
    </ship>
    <ship>
      <船舶種類>全貨櫃</船舶種類>
      <英文船名>WAN HAI 235</英文船名>
      <中文船名>民春</中文船名>
      <實際進港時間>110/05/23 23:50</實際進港時間>
    </ship>
    <ship>
      <船舶種類>油化船</船舶種類>
      <英文船名>SILVER SCORPIO</英文船名>
      <中文船名>銀蠍★★</中文船名>
      <實際進港時間>110/05/23 23:55</實際進港時間>
    </ship>
    <ship>
      <船舶種類>全貨櫃</船舶種類>
      <英文船名>KANWAY GLOBAL</英文船名>
      <中文船名>建輝</中文船名>
      <實際進港時間>110/05/24 00:01</實際進港時間>
    </ship>
    <ship>
      <船舶種類>油化船</船舶種類>
      <英文船名>CELSIUS BIRDIE</英文船名>
      <中文船名>柏蒂</中文船名>
      <實際進港時間>110/05/24 02:15</實際進港時間>
    </ship>
    <ship>
      <船舶種類>全貨櫃</船舶種類>
      <英文船名>A KIBO</英文船名>
      <中文船名>琪寶</中文船名>
      <實際進港時間>110/05/24 02:45</實際進港時間>
    </ship>
    <ship>
      <船舶種類>全貨櫃</船舶種類>
      <英文船名>EVER CHEER</英文船名>
      <中文船名>長采</中文船名>
      <實際進港時間>110/05/24 04:25</實際進港時間>
    </ship>
    <ship>
      <船舶種類>全貨櫃</船舶種類>
      <英文船名>HANSA DUBURG</英文船名>
      <中文船名>德翔都伯格</中文船名>
      <實際進港時間>110/05/24 04:25</實際進港時間>
    </ship>
    <ship>
      <船舶種類>多用途船</船舶種類>
      <英文船名>JJ STAR</英文船名>
      <中文船名>錦江之星</中文船名>
      <實際進港時間>110/05/24 05:25</實際進港時間>
    </ship>
    <ship>
      <船舶種類>全貨櫃</船舶種類>
      <英文船名>NORTHERN VOLITION</英文船名>
      <中文船名>神春輪</中文船名>
      <實際進港時間>110/05/24 06:30</實際進港時間>
    </ship>
    <ship>
      <船舶種類>冷凍船</船舶種類>
      <英文船名>TAISEI MARU NO.15</英文船名>
      <中文船名>第十五大盛丸★★</中文船名>
      <實際進港時間>110/05/24 06:45</實際進港時間>
    </ship>
    <ship>
      <船舶種類>雜貨船</船舶種類>
      <英文船名>DERYOUNG SUNNYSKY</英文船名>
      <中文船名>德洋向晴</中文船名>
      <實際進港時間>110/05/24 07:05</實際進港時間>
    </ship>
    <ship>
      <船舶種類>雜貨船</船舶種類>
      <英文船名>YUSHO EIGHT</英文船名>
      <中文船名>第八優昭★★</中文船名>
      <實際進港時間>110/05/24 07:10</實際進港時間>
    </ship>
  </data>
  <data name="最近24小時船舶實際出港時間">
    <ship>
      <船舶種類>全貨櫃</船舶種類>
      <英文船名>CMA CGM NIAGARA</英文船名>
      <中文船名>尼亞加拉</中文船名>
      <實際出港時間>110/05/23 07:37</實際出港時間>
    </ship>
    <ship>
      <船舶種類>油化船</船舶種類>
      <英文船名>AMAGI GALAXY</英文船名>
      <中文船名>天城號</中文船名>
      <實際出港時間>110/05/23 07:55</實際出港時間>
    </ship>
    <ship>
      <船舶種類>油輪</船舶種類>
      <英文船名>BAO SHAN NO.3</英文船名>
      <中文船名>寶山3號</中文船名>
      <實際出港時間>110/05/23 07:55</實際出港時間>
    </ship>
    <ship>
      <船舶種類>全貨櫃</船舶種類>
      <英文船名>RIO CADIZ</英文船名>
      <中文船名>加地斯</中文船名>
      <實際出港時間>110/05/23 08:03</實際出港時間>
    </ship>
    <ship>
      <船舶種類>多用途船</船舶種類>
      <英文船名>JJ SUN</英文船名>
      <中文船名>錦江之光</中文船名>
      <實際出港時間>110/05/23 08:30</實際出港時間>
    </ship>
    <ship>
      <船舶種類>全貨櫃</船舶種類>
      <英文船名>KOTA LESTARI</英文船名>
      <中文船名>永城</中文船名>
      <實際出港時間>110/05/23 08:42</實際出港時間>
    </ship>
    <ship>
      <船舶種類>全貨櫃</船舶種類>
      <英文船名>UNI-PREMIER</英文船名>
      <中文船名>立揆</中文船名>
      <實際出港時間>110/05/23 09:50</實際出港時間>
    </ship>
    <ship>
      <船舶種類>全貨櫃</船舶種類>
      <英文船名>SETSU MARU</英文船名>
      <中文船名>節丸</中文船名>
      <實際出港時間>110/05/23 11:32</實際出港時間>
    </ship>
    <ship>
      <船舶種類>全貨櫃</船舶種類>
      <英文船名>XINDE KEELUNG</英文船名>
      <中文船名>中外運基隆快航</中文船名>
      <實際出港時間>110/05/23 11:35</實際出港時間>
    </ship>
    <ship>
      <船舶種類>駛上駛下船</船舶種類>
      <英文船名>MIYARABI II</英文船名>
      <中文船名>美童2號</中文船名>
      <實際出港時間>110/05/23 11:45</實際出港時間>
    </ship>
    <ship>
      <船舶種類>液化氣體船</船舶種類>
      <英文船名>GLOBAL PHENIX</英文船名>
      <中文船名>鳳凰</中文船名>
      <實際出港時間>110/05/23 11:46</實際出港時間>
    </ship>
    <ship>
      <船舶種類>全貨櫃</船舶種類>
      <英文船名>EVER CREATE</英文船名>
      <中文船名>長新</中文船名>
      <實際出港時間>110/05/23 12:01</實際出港時間>
    </ship>
    <ship>
      <船舶種類>全貨櫃</船舶種類>
      <英文船名>YM IDEALS</英文船名>
      <中文船名>英明</中文船名>
      <實際出港時間>110/05/23 12:24</實際出港時間>
    </ship>
    <ship>
      <船舶種類>雜貨船</船舶種類>
      <英文船名>CITRIODORA</英文船名>
      <中文船名>希多拉</中文船名>
      <實際出港時間>110/05/23 12:45</實際出港時間>
    </ship>
    <ship>
      <船舶種類>全貨櫃</船舶種類>
      <英文船名>FUTURE</英文船名>
      <中文船名>前景</中文船名>
      <實際出港時間>110/05/23 13:02</實際出港時間>
    </ship>
    <ship>
      <船舶種類>液化氣體船</船舶種類>
      <英文船名>BAI HUA YUAN</英文船名>
      <中文船名>百花源</中文船名>
      <實際出港時間>110/05/23 13:06</實際出港時間>
    </ship>
    <ship>
      <船舶種類>全貨櫃</船舶種類>
      <英文船名>EVER BALMY</英文船名>
      <中文船名>長芳</中文船名>
      <實際出港時間>110/05/23 13:18</實際出港時間>
    </ship>
    <ship>
      <船舶種類>全貨櫃</船舶種類>
      <英文船名>WAN HAI 275</英文船名>
      <中文船名>石春</中文船名>
      <實際出港時間>110/05/23 13:30</實際出港時間>
    </ship>
    <ship>
      <船舶種類>散裝船</船舶種類>
      <英文船名>ATAYAL BRAVE</英文船名>
      <中文船名>泰雅勇士</中文船名>
      <實際出港時間>110/05/23 14:07</實際出港時間>
    </ship>
    <ship>
      <船舶種類>雜貨船</船舶種類>
      <英文船名>TONG MAO 101</英文船名>
      <中文船名>同茂101</中文船名>
      <實際出港時間>110/05/23 16:00</實際出港時間>
    </ship>
    <ship>
      <船舶種類>全貨櫃</船舶種類>
      <英文船名>CAPE FERROL</英文船名>
      <中文船名>懷春輪</中文船名>
      <實際出港時間>110/05/23 16:09</實際出港時間>
    </ship>
    <ship>
      <船舶種類>全貨櫃</船舶種類>
      <英文船名>YM INAUGURATION</英文船名>
      <中文船名>遠明</中文船名>
      <實際出港時間>110/05/23 16:55</實際出港時間>
    </ship>
    <ship>
      <船舶種類>全貨櫃</船舶種類>
      <英文船名>EVER BURLY</英文船名>
      <中文船名>長康</中文船名>
      <實際出港時間>110/05/23 17:05</實際出港時間>
    </ship>
    <ship>
      <船舶種類>雜貨船</船舶種類>
      <英文船名>PRINCESS</英文船名>
      <中文船名>公主</中文船名>
      <實際出港時間>110/05/23 17:05</實際出港時間>
    </ship>
    <ship>
      <船舶種類>雜貨船</船舶種類>
      <英文船名>BUNGO PRINCESS</英文船名>
      <中文船名>邦克</中文船名>
      <實際出港時間>110/05/23 17:35</實際出港時間>
    </ship>
    <ship>
      <船舶種類>全貨櫃</船舶種類>
      <英文船名>MAERSK DAVAO</英文船名>
      <中文船名>麥司克達沃</中文船名>
      <實際出港時間>110/05/23 18:10</實際出港時間>
    </ship>
    <ship>
      <船舶種類>散裝船</船舶種類>
      <英文船名>FENG SHUN</英文船名>
      <中文船名>豐順</中文船名>
      <實際出港時間>110/05/23 18:15</實際出港時間>
    </ship>
    <ship>
      <船舶種類>散裝船</船舶種類>
      <英文船名>DERYOUNG SUNBRIGHT</英文船名>
      <中文船名>德洋向耀</中文船名>
      <實際出港時間>110/05/23 18:31</實際出港時間>
    </ship>
    <ship>
      <船舶種類>雜貨船</船舶種類>
      <英文船名>ZAMBALES</英文船名>
      <中文船名>珍寶</中文船名>
      <實際出港時間>110/05/23 18:35</實際出港時間>
    </ship>
    <ship>
      <船舶種類>全貨櫃</船舶種類>
      <英文船名>DONG FANG SHUN</英文船名>
      <中文船名>東方順</中文船名>
      <實際出港時間>110/05/23 19:40</實際出港時間>
    </ship>
    <ship>
      <船舶種類>全貨櫃</船舶種類>
      <英文船名>TENG YUN HE</英文船名>
      <中文船名>騰雲河</中文船名>
      <實際出港時間>110/05/23 20:00</實際出港時間>
    </ship>
    <ship>
      <船舶種類>全貨櫃</船舶種類>
      <英文船名>EVER FORWARD</英文船名>
      <中文船名>長程</中文船名>
      <實際出港時間>110/05/23 20:22</實際出港時間>
    </ship>
    <ship>
      <船舶種類>油化船</船舶種類>
      <英文船名>SUN JUPITER</英文船名>
      <中文船名>木星</中文船名>
      <實際出港時間>110/05/23 20:40</實際出港時間>
    </ship>
    <ship>
      <船舶種類>散裝船</船舶種類>
      <英文船名>CHINA STEEL PRESTIGE</英文船名>
      <中文船名>中鋼榮耀</中文船名>
      <實際出港時間>110/05/23 21:00</實際出港時間>
    </ship>
    <ship>
      <船舶種類>全貨櫃</船舶種類>
      <英文船名>FORMOSA CONTAINER NO.4</英文船名>
      <中文船名>台塑貨櫃4號</中文船名>
      <實際出港時間>110/05/23 21:35</實際出港時間>
    </ship>
    <ship>
      <船舶種類>雜貨船</船舶種類>
      <英文船名>GLORY PIONEER</英文船名>
      <中文船名>常榮</中文船名>
      <實際出港時間>110/05/23 22:05</實際出港時間>
    </ship>
    <ship>
      <船舶種類>雜貨船</船舶種類>
      <英文船名>QUEEN YAN</英文船名>
      <中文船名>坤燕</中文船名>
      <實際出港時間>110/05/23 22:12</實際出港時間>
    </ship>
    <ship>
      <船舶種類>全貨櫃</船舶種類>
      <英文船名>WAN HAI 215</英文船名>
      <中文船名>兆春</中文船名>
      <實際出港時間>110/05/23 22:35</實際出港時間>
    </ship>
    <ship>
      <船舶種類>油輪</船舶種類>
      <英文船名>TAIAN</英文船名>
      <中文船名>台安</中文船名>
      <實際出港時間>110/05/23 23:28</實際出港時間>
    </ship>
    <ship>
      <船舶種類>全貨櫃</船舶種類>
      <英文船名>WAN HAI 213</英文船名>
      <中文船名>恆春</中文船名>
      <實際出港時間>110/05/24 00:10</實際出港時間>
    </ship>
    <ship>
      <船舶種類>水泥船</船舶種類>
      <英文船名>ASIA CEMENT NO.1</英文船名>
      <中文船名>亞泥1號</中文船名>
      <實際出港時間>110/05/24 01:00</實際出港時間>
    </ship>
    <ship>
      <船舶種類>全貨櫃</船舶種類>
      <英文船名>HUA HANG 6</英文船名>
      <中文船名>華航6</中文船名>
      <實際出港時間>110/05/24 02:20</實際出港時間>
    </ship>
    <ship>
      <船舶種類>全貨櫃</船舶種類>
      <英文船名>HUA HANG 1</英文船名>
      <中文船名>華航1</中文船名>
      <實際出港時間>110/05/24 03:18</實際出港時間>
    </ship>
    <ship>
      <船舶種類>油化船</船舶種類>
      <英文船名>DING HENG 5</英文船名>
      <中文船名>鼎衡5</中文船名>
      <實際出港時間>110/05/24 05:05</實際出港時間>
    </ship>
    <ship>
      <船舶種類>油化船</船舶種類>
      <英文船名>NAVIG8 GALLANTRY</英文船名>
      <中文船名>納維格</中文船名>
      <實際出港時間>110/05/24 06:40</實際出港時間>
    </ship>
  </data>
</root>
